{"name":"Calculate the monthly payment of a loan","id":"loan-simulator;calculate-the-monthly-payment-of-a-loan","scenarioId":"loan_simulator:Calculate the monthly payment of a loan","methodName":"Calculate the monthly payment of a loan","testSteps":[{"number":1,"description":"1: Calculate the monthly payment of a loan ({loan_amount\u003d1000000, number_of_payments\u003d\"32 meses\", monthly_payment\u003d10000})","duration":5641,"startTime":"2024-11-17T11:02:11.809437-05:00[America/Bogota]","result":"ERROR","precondition":false,"level":0,"lineNumber":19,"children":[{"number":2,"description":"Given I am in the loan simulator page","duration":4082,"startTime":"2024-11-17T11:02:11.900510-05:00[America/Bogota]","result":"SUCCESS","precondition":false,"level":1,"children":[{"number":3,"description":"Cliente open the","duration":3955,"startTime":"2024-11-17T11:02:12.023359-05:00[America/Bogota]","result":"SUCCESS","precondition":false,"level":2,"children":[{"number":4,"description":"Cliente opens the Loan simulator page","duration":3939,"startTime":"2024-11-17T11:02:12.034017-05:00[America/Bogota]","result":"SUCCESS","precondition":false,"level":3}]}]},{"number":5,"description":"When I enter the loan amount 1000000","duration":1149,"startTime":"2024-11-17T11:02:15.983533-05:00[America/Bogota]","result":"SUCCESS","precondition":false,"level":1,"children":[{"number":6,"description":"Cliente enter loan amount","duration":1139,"startTime":"2024-11-17T11:02:15.991679-05:00[America/Bogota]","result":"SUCCESS","precondition":false,"level":2,"children":[{"number":7,"description":"Cliente clicks on LINK TO SIMULATE","duration":680,"startTime":"2024-11-17T11:02:16.005586-05:00[America/Bogota]","result":"SUCCESS","precondition":false,"level":3},{"number":8,"description":"Cliente enters \u00271000000\u0027 then hits [RETURN] into INPUT TEXT","duration":212,"startTime":"2024-11-17T11:02:16.916638-05:00[America/Bogota]","result":"SUCCESS","precondition":false,"level":3}]}]},{"number":9,"description":"And I choose the number of payments \"32 meses\"","duration":310,"startTime":"2024-11-17T11:02:17.133168-05:00[America/Bogota]","screenshots":[{"screenshot":"cf77b7d8f1fab8ab3b664e44b3c2385bae26db9118446c36d1741669e9492f6b.png","htmlSource":"pagesource6433420454074884675.html","timeStamp":1731859337441,"screenshotName":"cf77b7d8f1fab8ab3b664e44b3c2385bae26db9118446c36d1741669e9492f6b.png"}],"exception":{"errorType":"java.lang.NullPointerException","message":"Cannot invoke \"Object.getClass()\" because \"object\" is null","stackTrace":[{"declaringClass":"co.com.udea.calidad.pagos.interactions.ChooseDropdownValue","methodName":"withValue","fileName":"ChooseDropdownValue.java","lineNumber":55},{"declaringClass":"co.com.udea.calidad.pagos.stepdefinitions.LoanSimulatorStepDefinition","methodName":"I_choose_the_number_of_payments","fileName":"LoanSimulatorStepDefinition.java","lineNumber":52},{"declaringClass":"✽","methodName":"I choose the number of payments \"32 meses\"","fileName":"file:///Users/juand/Downloads/clase2/src/test/resources/features/loan_simulator.feature","lineNumber":14}]},"result":"ERROR","precondition":false,"level":1},{"number":10,"description":"Then I can see the monthly payment higher than 10000","duration":0,"startTime":"2024-11-17T11:02:17.445047-05:00[America/Bogota]","result":"SKIPPED","precondition":false,"level":1}]}],"userStory":{"id":"loan_simulator","storyName":"Loan Simulator","displayName":"Loan Simulator","path":"loan_simulator","pathElements":[{"name":"loan_simulator","description":""}],"narrative":"  As a user I want to know the monthly payment of a loan so that I can make a decision","type":"feature"},"title":"Calculate the monthly payment of a loan","description":"","startTime":"2024-11-17T11:02:11.803142-05:00[America/Bogota]","duration":4157,"testFailureCause":{"errorType":"java.lang.NullPointerException","message":"Cannot invoke \"Object.getClass()\" because \"object\" is null","stackTrace":[{"declaringClass":"co.com.udea.calidad.pagos.interactions.ChooseDropdownValue","methodName":"withValue","fileName":"ChooseDropdownValue.java","lineNumber":55},{"declaringClass":"co.com.udea.calidad.pagos.stepdefinitions.LoanSimulatorStepDefinition","methodName":"I_choose_the_number_of_payments","fileName":"LoanSimulatorStepDefinition.java","lineNumber":52},{"declaringClass":"✽","methodName":"I choose the number of payments \"32 meses\"","fileName":"file:///Users/juand/Downloads/clase2/src/test/resources/features/loan_simulator.feature","lineNumber":14}]},"testFailureClassname":"java.lang.NullPointerException","testFailureMessage":"Cannot invoke \"Object.getClass()\" because \"object\" is null","testFailureSummary":"ERROR;java.lang.NullPointerException;Cannot invoke \"Object.getClass()\" because \"object\" is null;ChooseDropdownValue.java","projectKey":"","annotatedResult":"ERROR","isManualTestingUpToDate":false,"dataTable":{"headers":["loan_amount","number_of_payments","monthly_payment"],"rows":[{"values":["1000000","\"32 meses\"","10000"],"lineNumber":19,"result":"ERROR"},{"values":["1000000","\"48 meses\"","10000"],"lineNumber":20,"result":"UNDEFINED"},{"values":["1000000","\"60 meses\"","10000"],"lineNumber":21,"result":"UNDEFINED"},{"values":["1000000","\"72 meses\"","10000"],"lineNumber":22,"result":"UNDEFINED"}],"predefinedRows":true,"scenarioOutline":"","dataSetDescriptors":[{"startRow":0,"rowCount":0,"name":"","description":""}]},"manual":false,"testSource":"Cucumber","actors":[{"name":"Cliente","can":["browse the web"]},{"name":"david","can":["browse the web"]}],"order":0,"result":"ERROR","scenarioOutline":"Given I am in the loan simulator page\nWhen I enter the loan amount \u003cloan_amount\u003e\nAnd I choose the number of payments \u003cnumber_of_payments\u003e\nThen I can see the monthly payment higher than \u003cmonthly_payment\u003e"}